finquant/Makefile
finquant/__init__.py
finquant/asset.py
finquant/data_types.py
finquant/efficient_frontier.py
finquant/exceptions.py
finquant/market.py
finquant/minimise_fun.py
finquant/monte_carlo.py
finquant/moving_average.py
finquant/portfolio.py
finquant/quants.py
finquant/returns.py
finquant/stock.py
finquant/type_utilities.py
finquant_enhanced-0.7.1.dist-info/METADATA
finquant_enhanced-0.7.1.dist-info/WHEEL
finquant_enhanced-0.7.1.dist-info/licenses/LICENSE.txt
finquant_enhanced-0.7.1.dist-info/RECORD
