Metadata-Version: 2.4
Name: finquant-enhanced
Version: 0.7.1
Summary: A program for financial portfolio management, analysis and optimisation
Project-URL: Homepage, https://github.com/l4b4r4b4b4/FinQuant
Project-URL: Documentation, https://finquant.readthedocs.io
Project-URL: Repository, https://github.com/l4b4r4b4b4/FinQuant
Project-URL: Issues, https://github.com/l4b4r4b4b4/FinQuant/issues
Project-URL: Upstream, https://github.com/fmilthaler/FinQuant
Author-email: Frank Milthaler <f.milthaler@gmail.com>, l4b4r4b4b4 <lucas.cansino@mail.de>
Maintainer-email: l4b4r4b4b4 <lucas.cansino@mail.de>
License: MIT
License-File: LICENSE.txt
Keywords: efficient frontier,finance,investment,monte carlo,numerical,optimisation,portfolio,quant,quantitative
Classifier: Development Status :: 4 - Beta
Classifier: Intended Audience :: Education
Classifier: Intended Audience :: Financial and Insurance Industry
Classifier: Intended Audience :: Other Audience
Classifier: Intended Audience :: Science/Research
Classifier: License :: OSI Approved :: MIT License
Classifier: Operating System :: OS Independent
Classifier: Programming Language :: Python :: 3 :: Only
Classifier: Programming Language :: Python :: 3.10
Classifier: Programming Language :: Python :: 3.11
Classifier: Programming Language :: Python :: 3.12
Classifier: Programming Language :: Python :: 3.13
Requires-Python: >=3.10
Requires-Dist: matplotlib>=3.0
Requires-Dist: numpy>=1.22.0
Requires-Dist: pandas>=2.0
Requires-Dist: quandl>=3.4.5
Requires-Dist: scikit-learn>=1.3.0
Requires-Dist: scipy>=1.2.0
Requires-Dist: yfinance>=0.1.43
